mooncake/__init__.py
mooncake/async_store.py
mooncake/cli.py
mooncake/cli_bench.py
mooncake/cli_client.py
mooncake/engine.so
mooncake/ep.py
mooncake/http_metadata_server.py
mooncake/libetcd_wrapper.so
mooncake/mooncake_client
mooncake/mooncake_config.py
mooncake/mooncake_connector_v1.py
mooncake/mooncake_ep_buffer.py
mooncake/mooncake_master
mooncake/mooncake_store_service.py
mooncake/store.so
mooncake/transfer_engine_bench
mooncake/transfer_engine_topology_dump.py
mooncake/vllm_v1_proxy_server.py
mooncake_transfer_engine_non_cuda.libs/libetcd_wrapper-55933a67.so
mooncake_transfer_engine_non_cuda.libs/libgflags-f3c7dc50.so.2.2.2
mooncake_transfer_engine_non_cuda.libs/libglog-c040a6f3.so.0.4.0
mooncake_transfer_engine_non_cuda.libs/libjsoncpp-7d699962.so.1.9.5
mooncake_transfer_engine_non_cuda.libs/libunwind-5d1f6f10.so.8.0.1
mooncake_transfer_engine_non_cuda.libs/libyaml-cpp-0ff4f621.so.0.7.0
mooncake_transfer_engine_non_cuda-0.3.8.post1.dist-info/METADATA
mooncake_transfer_engine_non_cuda-0.3.8.post1.dist-info/WHEEL
mooncake_transfer_engine_non_cuda-0.3.8.post1.dist-info/entry_points.txt
mooncake_transfer_engine_non_cuda-0.3.8.post1.dist-info/top_level.txt
mooncake_transfer_engine_non_cuda-0.3.8.post1.dist-info/RECORD
mooncake_transfer_engine_non_cuda-0.3.8.post1.dist-info/sboms/auditwheel.cdx.json
