Metadata-Version: 2.4
Name: mooncake-transfer-engine-non-cuda
Version: 0.3.8.post1
Summary: Python binding of a Mooncake library using pybind11 (Non-CUDA version)
Author: Mooncake Authors
Project-URL: Homepage, https://github.com/kvcache-ai/Mooncake
Project-URL: Documentation, https://github.com/kvcache-ai/Mooncake/tree/main/doc
Project-URL: Source, https://github.com/kvcache-ai/Mooncake
Project-URL: Issues, https://github.com/kvcache-ai/Mooncake/issues
Keywords: mooncake,data transfer,kv cache,llm inference,non-cuda
Classifier: Programming Language :: Python :: 3
Classifier: Programming Language :: C++
Classifier: Operating System :: POSIX :: Linux
Requires-Python: >=3.8
Requires-Dist: aiohttp
Requires-Dist: requests
